pyspline/__init__.py
pyspline/arrays.py
pyspline/basis.py
pyspline/formatter.py
pyspline/psplines.py
pyspline/psplines_inner.py
pyspline/py.typed
pyspline-0.0.1.dist-info/LICENSE
pyspline-0.0.1.dist-info/METADATA
pyspline-0.0.1.dist-info/WHEEL
pyspline-0.0.1.dist-info/top_level.txt
pyspline-0.0.1.dist-info/RECORD
