Metadata-Version: 2.1
Name: pyspline
Version: 0.0.1
Summary: P-splines smoothing
Maintainer-email: Steven Golovkine <steven_golovkine@icloud.com>
License: Copyright 2024 Steven Golovkine
Project-URL: homepage, https://github.com/StevenGolovkine/pyspline
Project-URL: documentation, https://pyspline.readthedocs.io
Project-URL: repository, https://github.com/StevenGolovkine/pyspline
Keywords: smoothing,psplines
Classifier: Intended Audience :: Science/Research
Classifier: License :: OSI Approved :: BSD License
Classifier: Programming Language :: Python :: 3.10
Classifier: Topic :: Scientific/Engineering :: Mathematics
Requires-Python: <4,>=3.10
License-File: LICENSE
Requires-Dist: numpy <2,>=1.24.0
Requires-Dist: scikit-learn >=1.2.0
Provides-Extra: docs
Requires-Dist: matplotlib ; extra == 'docs'
Requires-Dist: numpydoc ; extra == 'docs'
Requires-Dist: pydata-sphinx-theme ; extra == 'docs'
Requires-Dist: scikit-learn ; extra == 'docs'
Requires-Dist: scipy ; extra == 'docs'
Requires-Dist: setuptools >=41.2 ; extra == 'docs'
Requires-Dist: sphinx >=3 ; extra == 'docs'
Requires-Dist: sphinxawesome-theme ; extra == 'docs'
Requires-Dist: sphinx-gallery ; extra == 'docs'
Provides-Extra: test
